django_casscache/__init__.py
django_casscache/backend.py
django_casscache/management/__init__.py
django_casscache/management/commands/__init__.py
django_casscache/management/commands/cqlall.py
django_casscache-0.1.0.dist-info/DESCRIPTION.rst
django_casscache-0.1.0.dist-info/METADATA
django_casscache-0.1.0.dist-info/pydist.json
django_casscache-0.1.0.dist-info/RECORD
django_casscache-0.1.0.dist-info/top_level.txt
django_casscache-0.1.0.dist-info/WHEEL
django_casscache-0.1.0.dist-info/zip-safe
