Metadata-Version: 2.0
Name: django-casscache
Version: 0.1.0
Summary: Django backend for python-casscache
Home-page: https://github.com/mattrobenolt/django-casscache
Author: Matt Robenolt
Author-email: matt@ydekproductions.com
License: BSD
Platform: UNKNOWN
Classifier: Development Status :: 4 - Beta
Classifier: Intended Audience :: Developers
Classifier: License :: OSI Approved :: GNU General Public License (GPL)
Classifier: Operating System :: OS Independent
Classifier: Topic :: Software Development
Requires-Dist: casscache
